{
 "EngineType0": {
  "External": false,
  "Booster": false,
  "Main": {
   "Type": "Radial",
   "Cylinders": 18,
   "Mass": 1020.0,
   "Thrust": 10.7,
   "ThrottleBoost": 1.001,
   "AfterburnerBoost": 1.25,
   "RPMMin": 600.0,
   "RPMMax": 2700.0,
   "RPMAfterburner": 2700.0,
   "RPMMaxAllowed": 2880.0,
   "StandbyFriction": 0.15,
   "FuelConsumptionOnIdle": 0.35,
   "FuelConsumptionOnHalfThr": 0.23,
   "FuelConsumptionOnFullThr": 0.326,
   "FuelConsumptionOnWEP": 0.383,
   "CarbueretorType": 1,
   "CarbureutorCapacity": 0.41,
   "IsAutonomous": true,
   "MinThrMult": 0.075,
   "MaxThrMult": 1.0,
   "IsWaterCooled": false,
   "EngineInertiaMoment": 3.0,
   "RPMAmplitude0": [
    2200.0,
    0.0
   ],
   "RPMAmplitude1": [
    0.0,
    5.0
   ],
   "ThrottleRPMAuto0": [
    0.0,
    800.0
   ],
   "ThrottleRPMAuto1": [
    0.63,
    2100.0
   ],
   "ThrottleRPMAuto2": [
    0.88,
    2200.0
   ],
   "ThrottleRPMAuto3": [
    1.0,
    2400.0
   ],
   "ThrottleRPMAuto4": [
    1.1,
    2700.0
   ],
   "ShaftRPMMin": 800.0,
   "ShaftRPMMax": 2700.0,
   "ShaftRpmController": true,
   "Power": 1600.0,
   "ConsumptionOmegaMax": 1.05,
   "TorqueZeroOmegaMult": 3.0,
   "TurbineTimeConstant": 3.4,
   "ThrustMax": {
    "VelocityType": "TAS",
    "ThrustMax0": 2700.0
   },
   "WEP_rpm": 2700.0,
   "Mil_rpm": 2400.0,
   "default_RPM": 2700.0,
   "default_mil_RPM_EffectOnSupercharger": 1.2376562500000001,
   "WEP_mil_RPM_EffectOnSupercharger": 1.2376562500000001,
   "Octane_mp": 1,
   "WEP_mp": 1.654,
   "Mil_mp": 1.364,
   "crit_supercharger_strength0": 1.3146663744034983,
   "deck_supercharger_strength0": 1.102083070319404,
   "Deck_Altitude0": -1835.3781938664536,
   "Power0": 1545.130315500686,
   "crit_supercharger_strength1": 1.9739091364992158,
   "deck_supercharger_strength1": 1.102083070319404,
   "Deck_Altitude1": -1835.3781938664536,
   "Power1": 1056.5864999394971
  },
  "AutoThrottle": {
   "HasContorller": false,
   "ThrottleOmegaPidInputLim": 1000000000.0,
   "ContorllerKp": 1e-06,
   "ContorllerKi": 1e-05,
   "ContorllerImax": 1.0,
   "ContorllerKd": 1.5e-05,
   "ContorllerDTau": 0.02
  },
  "Afterburner": {
   "IsControllable": true,
   "Type": 6,
   "NitroConsumption": 0.0
  },
  "Controls": {
   "hasThrottleControl": true,
   "hasMagnetoControl": true,
   "hasRadiatorControl": true,
   "hasOilRadiatorControl": false,
   "hasCommonRadiator": false,
   "hasVtolControl": false,
   "hasThrustReverseControl": false,
   "dvVtol": 0.2,
   "dvThrustRev": 0.2,
   "vtolToThrottleLim": [
    0.0,
    1.1,
    1.0,
    1.1
   ],
   "requireGearContactForReverseThrust": false,
   "reverseToThrottleLim": [
    0.0,
    1.1,
    1.0,
    1.1
   ],
   "iasToVtolLim": [
    0.0,
    1.0,
    0.0,
    1.0
   ]
  },
  "Temperature": {
   "OilRadiatorAuto": true,
   "RadiatorAuto": true,
   "NoIgnitionWaterHeatProducingFactor": 0.15,
   "WaterRadiatorEffectPower": 5.0,
   "WaterMinRadiatorThermalConductionCoeff": 0.81,
   "WaterMinThermostatThermalConductionCoeff": 0.3,
   "WaterMinLevelThermalConductionCoeff": 0.2,
   "WaterThermalConductionCrossCoeffTable": [
    0.4,
    0.2,
    0.02,
    0.2
   ],
   "WaterBoilingTemperature": 310.0,
   "WaterThermostatInertia": 20.0,
   "WaterThermostatSetPoint": 80.0,
   "NoFlowMode": 2,
   "NoIgnitionOilHeatProducingFactor": 0.15,
   "OilRadiatorEffectPower": 5.0,
   "OilMinRadiatorThermalConductionCoeff": 0.67,
   "OilMinThermostatThermalConductionCoeff": 0.3,
   "OilMinLevelThermalConductionCoeff": 0.2,
   "OilThermalConductionCrossCoeffTable": [
    0.4,
    0.2,
    0.02,
    0.2
   ],
   "OilBoilingTemperature": 160.0,
   "OilThermostatInertia": 20.0,
   "OilThermostatSetPoint": 30.0,
   "DegradationTime_10_5": [
    180.0,
    171.0
   ],
   "HalfHealthWaterTemperatureToleranceDecrease": 25.5,
   "HalfHealthOilTemperatureToleranceDecrease": 9.5,
   "WaterAirDensityPower": 0.02,
   "OilAirDensityPower": -0.02,
   "WaterFlowEffectPower": 4.0,
   "OilFlowEffectPower": 4.0,
   "WaterPropFlowSpeedCoeff": 0.8,
   "OilPropFlowSpeedCoeff": 0.5,
   "CoolingEffectiveAirSpeed": 320.0,
   "WaterTemperatureNoFlow": 290.0,
   "OilTemperatureNoFlow": 114.637,
   "WaterTemperatureInertia": 0.7,
   "OilTemperatureInertia": 3.5,
   "Mode0": {
    "Altitude": 1000.0,
    "RPM": 700.0,
    "ManifoldPressure": 0.3,
    "WaterTemperature": 115.0,
    "OilTemperature": 34.9199
   },
   "Mode1": {
    "Altitude": 1000.0,
    "RPM": 2100.0,
    "ManifoldPressure": 1.0,
    "WaterTemperature": 196.0,
    "OilTemperature": 54.8425
   },
   "Mode2": {
    "Altitude": 1000.0,
    "RPM": 2400.0,
    "ManifoldPressure": 1.48,
    "WaterTemperature": 230.0,
    "OilTemperature": 80.0
   },
   "Mode3": {
    "Altitude": 1000.0,
    "RPM": 2700.0,
    "ManifoldPressure": 1.654,
    "WaterTemperature": 251.0,
    "OilTemperature": 86.7285
   },
   "Load0": {
    "WaterTemperature": 220.0,
    "OilTemperature": 85.0
   },
   "Load1": {
    "WaterTemperature": 225.0,
    "OilTemperature": 88.0,
    "WorkTime": 7200.0,
    "RecoverTime": 310.0
   },
   "Load2": {
    "WaterTemperature": 235.0,
    "OilTemperature": 90.0,
    "WorkTime": 1800.0,
    "RecoverTime": 300.0
   },
   "Load3": {
    "WaterTemperature": 260.0,
    "OilTemperature": 95.0,
    "WorkTime": 300.0,
    "RecoverTime": 200.0
   },
   "Load4": {
    "WaterTemperature": 280.0,
    "OilTemperature": 105.0,
    "WorkTime": 120.0,
    "RecoverTime": 90.0
   },
   "RadiatorMode0": {
    "Throttle": 0.88,
    "WaterTemperature": 218.0,
    "OilTemperature": 80.0
   },
   "RadiatorMode1": {
    "Throttle": 1.0,
    "WaterTemperature": 230.0,
    "OilTemperature": 85.0
   },
   "RadiatorMode2": {
    "Throttle": 1.1,
    "WaterTemperature": 260.0,
    "OilTemperature": 95.0
   }
  },
  "Compressor": {
   "IsControllable": true,
   "Type": 1,
   "NumSteps": 2,
   "RPM0": 700.0,
   "ATA0": 0.3,
   "RPM1": 1800.0,
   "ATA1": 0.8,
   "RPM2": 2100.0,
   "ATA2": 1.0,
   "RPM3": 2300.0,
   "ATA3": 1.17,
   "RPM4": 2400.0,
   "ATA4": 1.364,
   "ExactAltitudes": true,
   "CompressorOmegaFactorSq": 1.0,
   "CompressorPressureAtRPM0": 0.1,
   "Altitude0": -312,
   "AfterburnerBoostMul0": 1.0,
   "Power0": 1545.130315500686,
   "AltitudeConstRPM0": 1463.0,
   "PowerConstRPM0": 1545.130315500686,
   "PowerConstRPMCurvature0": 1.0,
   "Ceiling0": -311,
   "PowerAtCeiling0": 1599.0,
   "Altitude1": 3010,
   "AfterburnerBoostMul1": 0.885,
   "Power1": 1448.5596707818931,
   "AltitudeConstRPM1": 1.0,
   "PowerConstRPM1": 1448.5596707818931,
   "PowerConstRPMCurvature1": 1.0,
   "Ceiling1": 3011,
   "PowerAtCeiling1": 1449.0,
   "AfterburnerManifoldPressure": 1.654,
   "SpeedManifoldMultiplier": 1.0,
   "AllowAutoTurboCharger": false,
   "TurboChargerRPMMin": 0.0,
   "TurboChargerRPMMaxAllowed": 18250.0,
   "TurboChargerRPMMax": 25000.0,
   "TurboChargerTimeConst": 1.0,
   "Old_Power0": 1600.0,
   "Old_Power_new_RPM0": 1545.130315500686,
   "Old_Altitude0": 1463.0,
   "Old_Ceiling0": 1463.5,
   "Old_PowerConstRPM0": 1600.0,
   "Old_PowerAtCeiling0": 1599.0,
   "Old_Power1": 1500.0,
   "Old_Power_new_RPM1": 1448.5596707818931,
   "Old_Altitude1": 4653.0,
   "Old_Ceiling1": 4653.5,
   "Old_PowerConstRPM1": 1500.0,
   "Old_PowerAtCeiling1": 1449.0
  },
  "Mixer": {
   "IsControllable": true,
   "Type": 1,
   "AltitudePressureToP0": 0.45
  },
  "Stages": {
   "Stage1": {
    "minTime": 1.0,
    "maxTime": 1.5,
    "fromRPM": 0.0,
    "toRPM": 10.0,
    "fromSuperchargerRPM": 0.0,
    "toSuperchargerRPM": 0.0
   },
   "Stage2": {
    "minTime": 3.0,
    "maxTime": 4.2,
    "fromRPM": 10.0,
    "toRPM": 35.0,
    "fromSuperchargerRPM": 0.0,
    "toSuperchargerRPM": 0.0
   },
   "Stage3": {
    "minTime": 0.1,
    "maxTime": 0.2,
    "fromRPM": 35.0,
    "toRPM": 120.0,
    "fromSuperchargerRPM": 0.0,
    "toSuperchargerRPM": 0.0
   },
   "Stage4": {
    "minTime": 0.5,
    "maxTime": 1.0,
    "fromRPM": 120.0,
    "toRPM": 240.0,
    "fromSuperchargerRPM": 0.0,
    "toSuperchargerRPM": 0.0
   },
   "Stage5": {
    "minTime": 1.5,
    "maxTime": 2.0,
    "fromRPM": 240.0,
    "toRPM": 800.0,
    "fromSuperchargerRPM": 0.0,
    "toSuperchargerRPM": 0.0
   }
  },
  "FireExtinguisher": {
   "Num": 0,
   "UseTime": 5.0,
   "Power": 1000.0,
   "Automatic": false
  }
 },
 "EngineType1": {
  "External": false,
  "Booster": false,
  "Main": {
   "Type": "Radial",
   "Cylinders": 18,
   "Mass": 1020.0,
   "Thrust": 10.7,
   "ThrottleBoost": 1.001,
   "AfterburnerBoost": 1.25,
   "RPMMin": 600.0,
   "RPMMax": 2700.0,
   "RPMAfterburner": 2700.0,
   "RPMMaxAllowed": 2880.0,
   "StandbyFriction": 0.15,
   "FuelConsumptionOnIdle": 0.35,
   "FuelConsumptionOnHalfThr": 0.23,
   "FuelConsumptionOnFullThr": 0.31,
   "FuelConsumptionOnWEP": 0.32,
   "CarbueretorType": 1,
   "CarbureutorCapacity": 0.41,
   "IsAutonomous": true,
   "MinThrMult": 0.16,
   "MaxThrMult": 1.0,
   "IsWaterCooled": false,
   "EngineInertiaMoment": 3.0,
   "RPMAmplitude0": [
    2600.0,
    0.0
   ],
   "RPMAmplitude1": [
    0.0,
    5.0
   ],
   "ThrottleRPMAuto0": [
    0.0,
    800.0
   ],
   "ThrottleRPMAuto1": [
    0.63,
    2100.0
   ],
   "ThrottleRPMAuto2": [
    0.88,
    2200.0
   ],
   "ThrottleRPMAuto3": [
    1.0,
    2400.0
   ],
   "ThrottleRPMAuto4": [
    1.1,
    2700.0
   ],
   "ShaftRPMMin": 800.0,
   "ShaftRPMMax": 2700.0,
   "ShaftRpmController": true,
   "Power": 1600.0,
   "ConsumptionOmegaMax": 1.05,
   "TorqueZeroOmegaMult": 3.0,
   "TurbineTimeConstant": 3.4,
   "ThrustMax": {
    "VelocityType": "TAS",
    "ThrustMax0": 2700.0
   },
   "WEP_rpm": 2700.0,
   "Mil_rpm": 2400.0,
   "default_RPM": 2700.0,
   "default_mil_RPM_EffectOnSupercharger": 1.0,
   "WEP_mil_RPM_EffectOnSupercharger": 1.0,
   "Octane_mp": 1,
   "WEP_mp": 1.654,
   "Mil_mp": 1.364,
   "crit_supercharger_strength0": 1.6882858969913306,
   "deck_supercharger_strength0": 1.364,
   "Deck_Altitude0": 0.0,
   "Power0": 1545.130315500686,
   "crit_supercharger_strength1": 2.682603964310151,
   "deck_supercharger_strength1": 1.364,
   "Deck_Altitude1": 0.0,
   "Power1": 1193.713845939625
  },
  "AutoThrottle": {
   "HasContorller": false,
   "ThrottleOmegaPidInputLim": 1000000000.0,
   "ContorllerKp": 1e-06,
   "ContorllerKi": 1e-05,
   "ContorllerImax": 1.0,
   "ContorllerKd": 1.5e-05,
   "ContorllerDTau": 0.02
  },
  "Afterburner": {
   "IsControllable": true,
   "Type": 6,
   "NitroConsumption": 0.0
  },
  "Controls": {
   "hasThrottleControl": true,
   "hasMagnetoControl": true,
   "hasRadiatorControl": true,
   "hasOilRadiatorControl": false,
   "hasCommonRadiator": false,
   "hasVtolControl": false,
   "hasThrustReverseControl": false,
   "dvVtol": 0.2,
   "dvThrustRev": 0.2,
   "vtolToThrottleLim": [
    0.0,
    1.1,
    1.0,
    1.1
   ],
   "requireGearContactForReverseThrust": false,
   "reverseToThrottleLim": [
    0.0,
    1.1,
    1.0,
    1.1
   ],
   "iasToVtolLim": [
    0.0,
    1.0,
    0.0,
    1.0
   ]
  },
  "Temperature": {
   "OilRadiatorAuto": true,
   "RadiatorAuto": true,
   "NoIgnitionWaterHeatProducingFactor": 0.15,
   "WaterRadiatorEffectPower": 5.0,
   "WaterMinRadiatorThermalConductionCoeff": 0.81,
   "WaterMinThermostatThermalConductionCoeff": 0.3,
   "WaterMinLevelThermalConductionCoeff": 0.2,
   "WaterThermalConductionCrossCoeffTable": [
    0.4,
    0.2,
    0.02,
    0.2
   ],
   "WaterBoilingTemperature": 310.0,
   "WaterThermostatInertia": 20.0,
   "WaterThermostatSetPoint": 80.0,
   "NoFlowMode": 2,
   "NoIgnitionOilHeatProducingFactor": 0.15,
   "OilRadiatorEffectPower": 5.0,
   "OilMinRadiatorThermalConductionCoeff": 0.67,
   "OilMinThermostatThermalConductionCoeff": 0.3,
   "OilMinLevelThermalConductionCoeff": 0.2,
   "OilThermalConductionCrossCoeffTable": [
    0.4,
    0.2,
    0.02,
    0.2
   ],
   "OilBoilingTemperature": 160.0,
   "OilThermostatInertia": 20.0,
   "OilThermostatSetPoint": 30.0,
   "DegradationTime_10_5": [
    180.0,
    171.0
   ],
   "HalfHealthWaterTemperatureToleranceDecrease": 25.5,
   "HalfHealthOilTemperatureToleranceDecrease": 9.5,
   "WaterAirDensityPower": 0.02,
   "OilAirDensityPower": -0.02,
   "WaterFlowEffectPower": 4.0,
   "OilFlowEffectPower": 4.0,
   "WaterPropFlowSpeedCoeff": 0.8,
   "OilPropFlowSpeedCoeff": 0.5,
   "CoolingEffectiveAirSpeed": 320.0,
   "WaterTemperatureNoFlow": 290.0,
   "OilTemperatureNoFlow": 114.637,
   "WaterTemperatureInertia": 0.7,
   "OilTemperatureInertia": 3.5,
   "Mode0": {
    "Altitude": 1000.0,
    "RPM": 700.0,
    "ManifoldPressure": 0.3,
    "WaterTemperature": 115.0,
    "OilTemperature": 34.9199
   },
   "Mode1": {
    "Altitude": 1000.0,
    "RPM": 2100.0,
    "ManifoldPressure": 1.0,
    "WaterTemperature": 196.0,
    "OilTemperature": 54.8425
   },
   "Mode2": {
    "Altitude": 1000.0,
    "RPM": 2400.0,
    "ManifoldPressure": 1.3,
    "WaterTemperature": 203.0,
    "OilTemperature": 71.7804
   },
   "Mode3": {
    "Altitude": 1000.0,
    "RPM": 2600.0,
    "ManifoldPressure": 1.48,
    "WaterTemperature": 247.0,
    "OilTemperature": 85.7319
   },
   "Mode4": {
    "Altitude": 1000.0,
    "RPM": 2601.0,
    "ManifoldPressure": 1.61,
    "WaterTemperature": 251.0,
    "OilTemperature": 86.7285
   },
   "Load0": {
    "WaterTemperature": 205.0,
    "OilTemperature": 60.0
   },
   "Load1": {
    "WaterTemperature": 218.0,
    "OilTemperature": 80.0,
    "WorkTime": 7200.0,
    "RecoverTime": 310.0
   },
   "Load2": {
    "WaterTemperature": 235.0,
    "OilTemperature": 87.0,
    "WorkTime": 1800.0,
    "RecoverTime": 300.0
   },
   "Load3": {
    "WaterTemperature": 260.0,
    "OilTemperature": 95.0,
    "WorkTime": 300.0,
    "RecoverTime": 200.0
   },
   "Load4": {
    "WaterTemperature": 280.0,
    "OilTemperature": 105.0,
    "WorkTime": 120.0,
    "RecoverTime": 90.0
   },
   "RadiatorMode0": {
    "Throttle": 0.88,
    "WaterTemperature": 218.0,
    "OilTemperature": 80.0
   },
   "RadiatorMode1": {
    "Throttle": 1.0,
    "WaterTemperature": 259.0,
    "OilTemperature": 94.0
   },
   "RadiatorMode2": {
    "Throttle": 1.1,
    "WaterTemperature": 259.5,
    "OilTemperature": 94.5
   }
  },
  "Compressor": {
   "IsControllable": true,
   "Type": 1,
   "NumSteps": 2,
   "RPM0": 700.0,
   "ATA0": 0.3,
   "RPM1": 1800.0,
   "ATA1": 0.8,
   "RPM2": 2100.0,
   "ATA2": 1.0,
   "RPM3": 2200.0,
   "ATA3": 1.3,
   "RPM4": 2400.0,
   "ATA4": 1.364,
   "ExactAltitudes": true,
   "CompressorOmegaFactorSq": 1.0,
   "CompressorPressureAtRPM0": 1.0,
   "Altitude0": 1763,
   "AfterburnerBoostMul0": 1.0,
   "Power0": 1545.130315500686,
   "AltitudeConstRPM0": 1763.0,
   "PowerConstRPM0": 1545.130315500686,
   "PowerConstRPMCurvature0": 1.0,
   "Ceiling0": 1763,
   "PowerAtCeiling0": 1599.0,
   "Altitude1": 5353,
   "AfterburnerBoostMul1": 0.885,
   "Power1": 1400.2743484224968,
   "AltitudeConstRPM1": 1.0,
   "PowerConstRPM1": 1400.2743484224968,
   "PowerConstRPMCurvature1": 1.0,
   "Ceiling1": 5354,
   "PowerAtCeiling1": 1449.0,
   "AfterburnerManifoldPressure": 1.654,
   "SpeedManifoldMultiplier": 1.0,
   "AllowAutoTurboCharger": false,
   "TurboChargerRPMMin": 0.0,
   "TurboChargerRPMMaxAllowed": 18250.0,
   "TurboChargerRPMMax": 25000.0,
   "TurboChargerTimeConst": 1.0,
   "Old_Power0": 1600.0,
   "Old_Power_new_RPM0": 1545.130315500686,
   "Old_Altitude0": 1763.0,
   "Old_Ceiling0": 1763.5,
   "Old_PowerConstRPM0": 1600.0,
   "Old_PowerAtCeiling0": 1599.0,
   "Old_Power1": 1450.0,
   "Old_Power_new_RPM1": 1400.2743484224968,
   "Old_Altitude1": 5353.0,
   "Old_Ceiling1": 5353.5,
   "Old_PowerConstRPM1": 1450.0,
   "Old_PowerAtCeiling1": 1449.0
  },
  "Mixer": {
   "IsControllable": true,
   "Type": 1,
   "AltitudePressureToP0": 0.45
  },
  "Stages": {
   "Stage1": {
    "minTime": 1.0,
    "maxTime": 1.5,
    "fromRPM": 0.0,
    "toRPM": 10.0,
    "fromSuperchargerRPM": 0.0,
    "toSuperchargerRPM": 0.0
   },
   "Stage2": {
    "minTime": 3.0,
    "maxTime": 4.2,
    "fromRPM": 10.0,
    "toRPM": 35.0,
    "fromSuperchargerRPM": 0.0,
    "toSuperchargerRPM": 0.0
   },
   "Stage3": {
    "minTime": 0.1,
    "maxTime": 0.2,
    "fromRPM": 35.0,
    "toRPM": 120.0,
    "fromSuperchargerRPM": 0.0,
    "toSuperchargerRPM": 0.0
   },
   "Stage4": {
    "minTime": 0.5,
    "maxTime": 1.0,
    "fromRPM": 120.0,
    "toRPM": 240.0,
    "fromSuperchargerRPM": 0.0,
    "toSuperchargerRPM": 0.0
   },
   "Stage5": {
    "minTime": 1.5,
    "maxTime": 2.0,
    "fromRPM": 240.0,
    "toRPM": 800.0,
    "fromSuperchargerRPM": 0.0,
    "toSuperchargerRPM": 0.0
   }
  },
  "FireExtinguisher": {
   "Num": 0,
   "UseTime": 5.0,
   "Power": 1000.0,
   "Automatic": false
  }
 },
 "Engine0": {
  "Type": 0,
  "Main": {
   "FuelSystemNum": 0
  },
  "Nozzle0": {
   "Position": [
    2.92,
    0.0,
    2.97
   ],
   "Direction": [
    -0.0,
    0.0
   ],
   "Direction2": [
    -90.0,
    -0.0
   ],
   "ThrustRatio": 1.0,
   "ThrustMax": 2147440000.0,
   "TipPosition": false,
   "AileronsToThrustDeflection": [
    0.0,
    0.0,
    0.0
   ],
   "ElevatorToThrustDeflection": [
    0.0,
    0.0,
    0.0
   ],
   "RudderToThrustDeflection": [
    0.0,
    0.0,
    0.0
   ],
   "VtolToThrustDeflection": [
    0.0,
    0.0
   ],
   "ReverseToThrustDeflection": [
    0.0,
    0.0
   ],
   "AileronsToThrust": [
    0.0,
    0.0,
    0.0
   ],
   "ElevatorToThrust": [
    0.0,
    0.0,
    0.0
   ],
   "RudderToThrust": [
    0.0,
    0.0,
    0.0
   ],
   "AirbrakeToThrust": [
    0.0,
    0.0
   ],
   "VtolToThrust": [
    0.0,
    0.0
   ],
   "ReverseToThrust": [
    0.0,
    0.0
   ],
   "FlapsToThrust": [
    0.0,
    1.0,
    1.0,
    1.0
   ]
  }
 },
 "Engine1": {
  "Type": 0,
  "Main": {
   "FuelSystemNum": 0
  },
  "Nozzle0": {
   "Position": [
    2.92,
    0.0,
    -2.97
   ],
   "Direction": [
    -0.0,
    0.0
   ],
   "Direction2": [
    -90.0,
    -0.0
   ],
   "ThrustRatio": 1.0,
   "ThrustMax": 2147440000.0,
   "TipPosition": false,
   "AileronsToThrustDeflection": [
    0.0,
    0.0,
    0.0
   ],
   "ElevatorToThrustDeflection": [
    0.0,
    0.0,
    0.0
   ],
   "RudderToThrustDeflection": [
    0.0,
    0.0,
    0.0
   ],
   "VtolToThrustDeflection": [
    0.0,
    0.0
   ],
   "ReverseToThrustDeflection": [
    0.0,
    0.0
   ],
   "AileronsToThrust": [
    0.0,
    0.0,
    0.0
   ],
   "ElevatorToThrust": [
    0.0,
    0.0,
    0.0
   ],
   "RudderToThrust": [
    0.0,
    0.0,
    0.0
   ],
   "AirbrakeToThrust": [
    0.0,
    0.0
   ],
   "VtolToThrust": [
    0.0,
    0.0
   ],
   "ReverseToThrust": [
    0.0,
    0.0
   ],
   "FlapsToThrust": [
    0.0,
    1.0,
    1.0,
    1.0
   ]
  }
 },
 "Propeller0": {
  "Type": 0,
  "AxisDirection": [
   -0.0,
   0.0
  ],
  "CyclicPitchAxisDirectionPitch": [
   -180.0,
   90.0
  ],
  "Pos": [
   3.45,
   0.0,
   3.33
  ],
  "Geometry": {
   "RotationDirection": 1
  }
 },
 "Mass": {
  "EmptyMass": 9687.0,
  "FuelAccumulatorCapacity0": 2.2,
  "MinimalLoadFactor0": 0.0,
  "FuelAccumulatorFlowRate0": 0.38,
  "FuelEngineFlowRate0": 0.38,
  "MaxNitro": 0.0,
  "OilMass": 142.88,
  "AdvancedMass": false,
  "doesPayloadAffectCOG": false,
  "SeparateFuelTanks": true,
  "Takeoff": 17016.0,
  "CenterOfGravity": [
   -0.3,
   0.0,
   0.0
  ],
  "GearDestructionIndSpeed": 265.0,
  "AirbrakeDestructionIndSpeed": -1.0,
  "FlapsDestructionIndSpeedP0": [
   0.1,
   430.0
  ],
  "FlapsDestructionIndSpeedP1": [
   0.33,
   320.0
  ],
  "FlapsDestructionIndSpeedP2": [
   1.0,
   297.0
  ],
  "Parts": {
   "tank1_capacity": 286.5,
   "tank1_system": 0,
   "tank1_external": false,
   "tank1_priority": 0,
   "tank2_capacity": 1079.0,
   "tank2_system": 0,
   "tank2_external": false,
   "tank2_priority": 1,
   "tank3_capacity": 1079.0,
   "tank3_system": 0,
   "tank3_external": false,
   "tank3_priority": 1,
   "tank4_capacity": 286.5,
   "tank4_system": 0,
   "tank4_external": false,
   "tank4_priority": 0,
   "armor5_dm": 14.0,
   "aileron_l_dm": 25.0,
   "cover5_dm": 1.2,
   "cover6_dm": 1.2,
   "gear_l_dm": 220.0,
   "flap_l_dm": 55.0,
   "flap1_l_dm": 45.0,
   "tail_dm": 200.0,
   "gun1_dm": 27.0,
   "cover3_dm": 75.0,
   "cover1_dm": 550.0,
   "cover2_dm": 550.0,
   "fuse_dm": 300.0,
   "fuse1_dm": 400.0,
   "cover7_dm": 1.2,
   "wing_l_dm": 526.208,
   "wing1_l_dm": 333.408,
   "spar_l_dm": 125.165,
   "flap1_r_dm": 45.0,
   "flap_r_dm": 55.0,
   "gear_r_dm": 220.0,
   "aileron_r_dm": 25.0,
   "wingcontrol_l_dm": 13.1847,
   "tailcontrol_dm": 16.8376,
   "pilot1_dm": 90.0,
   "pilot_dm": 90.0,
   "wing2_l_dm": 275.014,
   "fuse2_dm": 650.0,
   "engine1_dm": 1115.0,
   "gun5_dm": 27.0,
   "gear_c_dm": 75.0,
   "gunner2_dm": 90.0,
   "oil1_dm": 60.0,
   "oil2_dm": 67.0,
   "oil3_dm": 60.0,
   "oil4_dm": 67.0,
   "gunner3_dm": 90.0,
   "armor4_dm": 17.0,
   "mgun5_dm": 27.0,
   "mgun4_dm": 27.0,
   "gunner5_dm": 90.0,
   "gunner4_dm": 90.0,
   "engine2_dm": 1115.0,
   "gun4_dm": 27.0,
   "gun3_dm": 27.0,
   "gun2_dm": 27.0,
   "spar2_l_dm": 61.3229,
   "spar1_l_dm": 83.6041,
   "spar1_r_dm": 83.6041,
   "spar2_r_dm": 61.3229,
   "spar_r_dm": 125.165,
   "wing1_r_dm": 333.408,
   "wing2_r_dm": 275.014,
   "wing_r_dm": 526.208,
   "wingcontrol_r_dm": 12.9668,
   "cover4_dm": 1.2,
   "armor2_dm": 75.0,
   "armor6_dm": 7.0,
   "armor7_dm": 7.0,
   "armor3_dm": 25.0,
   "armor1_dm": 75.0
  },
  "PartsWithSurface": {
   "elevator1_dm": 0.385161,
   "fin_dm": 0.424855,
   "stab1_dm": 0.449526,
   "rudder_dm": 0.44637,
   "elevator0_dm": 0.385161,
   "gunner6_dm": 0.122367,
   "mgun2_dm": 0.060154,
   "mgun3_dm": 0.0600053,
   "armor8_dm": 0.0428406,
   "armor9_dm": 0.0428406,
   "stab2_dm": 0.449526,
   "mgun1_dm": 0.0637541,
   "cover8_dm": 0.0586118
  },
  "MaxFuelMass": 2731.0,
  "pilots_mass": 540
 },
 "engine_count": 2,
 "Modif": {
  "cd_98": {},
  "CdMin_Fuse": {},
  "new_cover": {},
  "structure_str": {},
  "hp_105": {},
  "new_radiator": {},
  "new_compressor": {},
  "new_engine_injection": {}
 },
 "Guns": {
  "gunBrowning50_turret.blk": {
   "ammo_count": 3150,
   "gun_count": 7,
   "shell_mass": 0.044128053
  },
  "gunBrowning50.blk": {
   "ammo_count": 1100,
   "gun_count": 5,
   "shell_mass": 0.044128053
  },
  "us_100lb_anm30.blk": {
   "ammo_count": 30,
   "gun_count": 30
  },
  "all_ammo_mass": 187
 },
 "engines_are_same": false
}